Metadata-Version: 2.1
Name: slim_gsgp
Version: 0.1.10
Summary: Semantic Learning algorithm based on Inflate and deflate Mutation (SLIM GSGP)
Home-page: https://github.com/DALabNOVA/slim
Author: Liah Rosenfeld, Davide Farinati, Diogo Rasteiro, Gloria Pietropolli, Karina Brotto Rebulli, Sara Silva, Leonardo Vanneschi
Author-email: lrosenfeld@novaims.unl.pt, dfarinati@novaims.unl.pt, drasteiro@novaims.unl.pt, gloria.pietropolli@phd.units.it, karina.brottorebuli@unito.it, sgsilva@fc.ul.pt, lvanneschi@novaims.unl.pt
Classifier: Programming Language :: Python :: 3
Classifier: License :: OSI Approved :: MIT License
Classifier: Operating System :: OS Independent
Requires-Python: >=3.10
License-File: LICENSE
Requires-Dist: numpy
Requires-Dist: pandas
Requires-Dist: torch
Requires-Dist: scipy
Requires-Dist: scikit-learn
Requires-Dist: joblib
